[
    {
        "id": "_meta",
        "name": "Art Thou Evil, Sir?",
        "author": "Ben Burns",
        "logo": "https://github.com/gitorcat/BOTCH/blob/main/art/BuddiesBuddies.png?raw=true"
    },
    "investigator",
    "clockmaker",
    "noble",
    "sailor",
    "empath",
    "monk",
    "gambler",
    "oracle",
    "gossip",
    "huntsman",
    "mayor",
    "farmer",
    "amnesiac",
    "damsel",
    "lunatic",
    "puzzlemaster",
    {
        "id": "ogre",
        "image": "https://github.com/gitorcat/BOTCH/blob/main/art/icons/pandemonium_institute/ogre.png?raw=true",
        "edition": "experimental",
        "firstNight": 2,
        "firstNightReminder": "The Ogre points to a player. If that player is evil, mark the Ogre with an 'Evil' reminder.",
        "otherNight": 0,
        "otherNightReminder": "",
        "reminders": [],
        "remindersGlobal": [],
        "setup": false,
        "name": "Ogre",
        "team": "outsider",
        "ability": "On your 1st night, choose a player (not yourself): you become their alignment (you don't know which) even if drunk or poisoned."
    },
    "devilsadvocate",
    "marionette",
    {
        "id": "summoner",
        "image": "https://github.com/gitorcat/BOTCH/blob/main/art/icons/pandemonium_institute/summoner.png?raw=true",
        "edition": "experimental",
        "firstNight": 10,
        "firstNightReminder": "Wake the Summoner and show them three not-in-play character tokens.",
        "otherNight": 2,
        "otherNightReminder": "If the Summoner has a 'Night 3' reminder. Wake the Summoner. They point at a player, and to a Demon icon on the character sheet. Put the Summoner to sleep. Wake the chosen player. Show the 'You are' card, the thumbs down evil sign, and the Demon token. Replace their character token with the Demon token and put the new Demon to sleep.",
        "reminders": ["Night 1", "Night 2", "Night 3"],
        "remindersGlobal": [],
        "setup": true,
        "name": "Summoner",
        "team": "minion",
        "ability": "You get 3 bluffs. On the 3rd night, choose a player: they become an evil Demon of your choice. [No Demon]"
    },
    "baron",
    {
        "id": "ojo",
        "image": "https://github.com/gitorcat/BOTCH/blob/main/art/icons/pandemonium_institute/ojo.png?raw=true",
        "edition": "experimental",
        "firstNight": 0,
        "firstNightReminder": "",
        "otherNight": 24,
        "otherNightReminder": "The Ojo points to a character. That character, if in play, dies. If that character is not in play, choose zero, one, or more players to die.",
        "reminders": ["Dead"],
        "remindersGlobal": [],
        "setup": false,
        "name": "Ojo",
        "team": "demon",
        "ability": "Each night*, choose a character: they die. If they are not in play, the Storyteller chooses who dies."
    },
    {
        "id": "littlemonster",
        "image": "https://github.com/bra1n/townsquare/blob/develop/src/assets/icons/lilmonsta.png?raw=true",
        "edition": "experimental",
        "firstNight": 15,
        "firstNightReminder": "Wake all Minions together, allow them to vote by pointing at who they want to babysit Lil' Monsta.",
        "otherNight": 35,
        "otherNightReminder": "Wake all Minions together, allow them to vote by pointing at who they want to babysit Lil' Monsta. Choose a player, that player dies.",
        "reminders": ["Is the Demon", "Dead"],
        "remindersGlobal": [],
        "setup": false,
        "name": "Lil' Monsta",
        "team": "demon",
        "ability": "Each night, Minions choose who babysits Lil' Monsta's token & \"is the Demon\". Each night*, a player might die. [+1 Minion]"
    },
    "legion",
    "vigormortis"
]